I/__main__.py
i_will-0.1.1.dist-info/entry_points.txt
i_will-0.1.1.dist-info/METADATA
i_will-0.1.1.dist-info/WHEEL
i_will-0.1.1.dist-info/RECORD
